jade_client-1.0.35.dist-info/licenses/COPYING
jade_client-1.0.35.dist-info/licenses/LICENSE
jadepy/__init__.py
jadepy/jade.py
jadepy/jade_ble.py
jadepy/jade_error.py
jadepy/jade_serial.py
jadepy/jade_tcp.py
jade_client-1.0.35.dist-info/METADATA
jade_client-1.0.35.dist-info/WHEEL
jade_client-1.0.35.dist-info/top_level.txt
jade_client-1.0.35.dist-info/RECORD
